visier/__init__.py
visier/sdk/__init__.py
visier/sdk/api/__init__.py
visier/sdk/api/core/__init__.py
visier/sdk/api/core/api_client.py
visier/sdk/api/core/api_response.py
visier/sdk/api/core/configuration.py
visier/sdk/api/core/exceptions.py
visier/sdk/api/core/py.typed
visier/sdk/api/core/rest.py
visier.sdk.api.core-0.0.202.dist-info/METADATA
visier.sdk.api.core-0.0.202.dist-info/WHEEL
visier.sdk.api.core-0.0.202.dist-info/top_level.txt
visier.sdk.api.core-0.0.202.dist-info/RECORD
