Metadata-Version: 2.1
Name: visier.sdk.api.core
Version: 0.0.202
Summary: Visier Authentication APIs
Home-page: 
Author: OpenAPI Generator community
Author-email: team@openapitools.org
License: Apache License, Version 2.0
Keywords: OpenAPI,OpenAPI-Generator,Visier Authentication APIs
Requires-Dist: urllib3 <2.1.0,>=1.25.3
Requires-Dist: python-dateutil
Requires-Dist: Flask >=3.0.0
Requires-Dist: pydantic >=2
Requires-Dist: typing-extensions >=4.7.1
